pyadmin/__init__.py
pyadmin/example.py
pyadmin-0.0.1.dist-info/LICENSE
pyadmin-0.0.1.dist-info/METADATA
pyadmin-0.0.1.dist-info/WHEEL
pyadmin-0.0.1.dist-info/top_level.txt
pyadmin-0.0.1.dist-info/RECORD
